gosti/__init__.py
gosti/basic/aid.py
gosti/basic/angle_2d.py
gosti/basic/elliptical_radii.py
gosti/basic/ortho_basis.py
gosti/basic/point_2d.py
gosti/basic/point_3d.py
gosti/basic/unit_vector2d.py
gosti/basic/unit_vector3d.py
gosti/basic/vec_2d.py
gosti/basic/vec_3d.py
gosti/basic/vector_2d.py
gosti/basic/vector_3d.py
gosti/dispertion/dispersion_schott.py
gosti/dispertion/dispertion.py
gosti/dispertion/refractive_index.py
gosti/fft_psf/__init__.py
gosti/fft_psf/compute_fft_psf.py
gosti/fft_psf/fft_psf.py
gosti/fft_psf/fft_psf_from_array.py
gosti/fft_psf/fft_psf_from_zemax_report.py
gosti/fft_psf/fft_psf_old.py
gosti/fft_psf/parse_zemax.py
gosti/fft_psf/zemax_fft_psf_meta.py
gosti/grids/__init__.py
gosti/grids/angular_grid.py
gosti/psf/otf.py
gosti/psf/otf_builder.py
gosti/psf/psf.py
gosti/psf/psf_builder.py
gosti/pupil/apodization.py
gosti/pupil/apodizations.py
gosti/pupil/pupil_function.py
gosti/pupil/pupil_function_builder.py
gosti/pupil/pupil_grid.py
gosti/pupil/pupil_grid_old.py
gosti/pupil/pupil_mask.py
gosti/pupil/pupil_mask_elliptical.py
gosti/pupil/vis.py
gosti/ray/ray_3d.py
gosti/scalar2d/__init__.py
gosti/scalar2d/compare_scalar2d.py
gosti/scalar2d/resample_scalar2d.py
gosti/scalar2d/scalar_field2d.py
gosti/surface/Surface3d.py
gosti/surface/basis.py
gosti/surface/freeform_surface.py
gosti/wavefront/wavefront.py
gosti/wavefront/wavefront_builder.py
gosti/wavelength/__init__.py
gosti/wavelength/wavelength.py
gosti/zernike/__init__.py
gosti/zernike/parse_zenike_text.py
gosti/zernike/zernike_aid.py
gosti/zernike/zernike_base.py
gosti/zernike/zernike_projection.py
gosti/zernike/zernike_report.py
gosti/zernike/zernike_term.py
gosti-0.4.0.dist-info/licenses/LICENSE
gosti-0.4.0.dist-info/METADATA
gosti-0.4.0.dist-info/WHEEL
gosti-0.4.0.dist-info/top_level.txt
gosti-0.4.0.dist-info/RECORD
